minionpy/cec.py
minionpy/algorithms.py
minionpy/__init__.py
minionpy/cec_2011.py
minionpy/test_functions.py
minionpy/parallel.py
minionpy/cec_input_data/input_data_2022/shift_data_10.txt
minionpy/cec_input_data/input_data_2022/shift_data_11.txt
minionpy/cec_input_data/input_data_2022/M_7_D10.txt
minionpy/cec_input_data/input_data_2022/M_2_D20.txt
minionpy/cec_input_data/input_data_2022/shuffle_data_8_D10.txt
minionpy/cec_input_data/input_data_2022/shift_data_12.txt
minionpy/cec_input_data/input_data_2022/M_12_D10.txt
minionpy/cec_input_data/input_data_2022/M_5_D2.txt
minionpy/cec_input_data/input_data_2022/M_6_D10.txt
minionpy/cec_input_data/input_data_2022/M_9_D2.txt
minionpy/cec_input_data/input_data_2022/M_3_D20.txt
minionpy/cec_input_data/input_data_2022/M_10_D10.txt
minionpy/cec_input_data/input_data_2022/shift_data_5.txt
minionpy/cec_input_data/input_data_2022/M_4_D10.txt
minionpy/cec_input_data/input_data_2022/shift_data_4.txt
minionpy/cec_input_data/input_data_2022/M_1_D20.txt
minionpy/cec_input_data/input_data_2022/M_1_D2.txt
minionpy/cec_input_data/input_data_2022/shuffle_data_7_D20.txt
minionpy/cec_input_data/input_data_2022/shift_data_6.txt
minionpy/cec_input_data/input_data_2022/M_8_D20.txt
minionpy/cec_input_data/input_data_2022/shift_data_7.txt
minionpy/cec_input_data/input_data_2022/shuffle_data_6_D20.txt
minionpy/cec_input_data/input_data_2022/M_11_D2.txt
minionpy/cec_input_data/input_data_2022/shift_data_3.txt
minionpy/cec_input_data/input_data_2022/M_9_D20.txt
minionpy/cec_input_data/input_data_2022/shift_data_2.txt
minionpy/cec_input_data/input_data_2022/M_5_D10.txt
minionpy/cec_input_data/input_data_2022/M_11_D10.txt
minionpy/cec_input_data/input_data_2022/M_3_D2.txt
minionpy/cec_input_data/input_data_2022/shift_data_1.txt
minionpy/cec_input_data/input_data_2022/Rand_Seeds.txt
minionpy/cec_input_data/input_data_2022/M_5_D20.txt
minionpy/cec_input_data/input_data_2022/M_11_D20.txt
minionpy-1.0.1.dist-info/RECORD
minionpy-1.0.1.dist-info/WHEEL
minionpy-1.0.1.dist-info/top_level.txt
minionpy-1.0.1.dist-info/METADATA
