Metadata-Version: 2.4
Name: minionpy
Version: 1.0.1
Summary: MinionPy is the Python implementation of the Minion C++ library, designed for derivative-free optimization.
Author: Khoirul Faiq Muzakka
Author-email: Khoirul Faiq Muzakka <khoirul.muzakka@gmail.com>
License: MIT License
Project-URL: homepage, https://github.com/khoirulmuzakka/Minion
Project-URL: documentation, https://minion-py.readthedocs.io/
Project-URL: source, https://github.com/khoirulmuzakka/Minion
Classifier: Development Status :: 3 - Alpha
Classifier: Intended Audience :: Education
Classifier: Intended Audience :: Science/Research
Classifier: Intended Audience :: Developers
Classifier: Environment :: Console
Classifier: License :: OSI Approved :: MIT License
Classifier: Operating System :: MacOS :: MacOS X
Classifier: Operating System :: Microsoft :: Windows
Classifier: Operating System :: Unix
Classifier: Programming Language :: Python
Classifier: Programming Language :: Python :: 3
Classifier: Programming Language :: Python :: 3 :: Only
Classifier: Programming Language :: Python :: 3.9
Classifier: Programming Language :: Python :: 3.10
Classifier: Programming Language :: Python :: 3.11
Classifier: Programming Language :: Python :: 3.12
Classifier: Programming Language :: Python :: 3.13
Classifier: Topic :: Scientific/Engineering
Classifier: Topic :: Software Development
Requires-Python: >=3.8
Requires-Dist: numpy>=1.21.0
Dynamic: author
Dynamic: requires-python
